README.md
setup.cfg
setup.py
distributions_rmbg/Binomialdistribution.py
distributions_rmbg/Gaussiandistribution.py
distributions_rmbg/Generaldistribution.py
distributions_rmbg/__init__.py
distributions_rmbg.egg-info/PKG-INFO
distributions_rmbg.egg-info/SOURCES.txt
distributions_rmbg.egg-info/dependency_links.txt
distributions_rmbg.egg-info/not-zip-safe
distributions_rmbg.egg-info/top_level.txt